{
  "signals":
  [
    { "group": "Неисправность модулей прибора ШС5-1-1 - Входы (Уникальные)", "signals": [
      { "id": 33554432, "name": "102_SHS51_OperabilityM440_that",         "packid": "102", "params": { "byte": 0, "offset": 0, "len": 1, "tip": "discrete", "description": "Исправность модуля М440 (А1В1) парного канала" } },
      { "id": 33554433, "name": "102_SHS51_FaultMVA32_A1B5",              "packid": "102", "params": { "byte": 0, "offset": 1, "len": 1, "tip": "discrete", "description": "Неисправность модуля МВА32-1(А1В5) - обобщенная" } },
      { "id": 33554434, "name": "102_SHS51_ServiceableMMK20_A1B6p1",      "packid": "102", "params": { "byte": 0, "offset": 2, "len": 1, "tip": "discrete", "description": "Исправность ММК20 А1В6 в т.1" } },
      { "id": 33554435, "name": "102_SHS51_ServiceableMMK20_A1B6p2",      "packid": "102", "params": { "byte": 0, "offset": 3, "len": 1, "tip": "discrete", "description": "Исправность ММК20 А1В6 в т.2" } },
      { "id": 33554436, "name": "102_SHS51_ServiceableMMK20_A1B6p3",      "packid": "102", "params": { "byte": 0, "offset": 4, "len": 1, "tip": "discrete", "description": "Исправность ММК20 А1В6 в т.3" } },
      { "id": 33554437, "name": "102_SHS51_ServiceableMMK20_A1B6p4",      "packid": "102", "params": { "byte": 0, "offset": 5, "len": 1, "tip": "discrete", "description": "Исправность ММК20 А1В6 в т.4" } },
      { "id": 33554438, "name": "102_SHS51_FaultMMK20_A1B6",              "packid": "102", "params": { "byte": 0, "offset": 6, "len": 1, "tip": "discrete", "description": "Неисправность модуля ММК20 (А1В6) - обобщенная" } },
      { "id": 33554439, "name": "102_SHS51_ServiceableMMK20_A1B7p1",      "packid": "102", "params": { "byte": 0, "offset": 7, "len": 1, "tip": "discrete", "description": "Исправность ММК20 А1В7 в т.1" } },
      { "id": 33554688, "name": "102_SHS51_ServiceableMMK20_A1B7p2",      "packid": "102", "params": { "byte": 1, "offset": 0, "len": 1, "tip": "discrete", "description": "Исправность ММК20 А1В7 в т.2" } },
      { "id": 33554689, "name": "102_SHS51_ServiceableMMK20_A1B7p3",      "packid": "102", "params": { "byte": 1, "offset": 1, "len": 1, "tip": "discrete", "description": "Исправность ММК20 А1В7 в т.3" } },
      { "id": 33554690, "name": "102_SHS51_ServiceableMMK20_A1B7p4",      "packid": "102", "params": { "byte": 1, "offset": 2, "len": 1, "tip": "discrete", "description": "Исправность ММК20 А1В7 в т.4" } },
      { "id": 33554691, "name": "102_SHS51_FaultMMK20_A1B7",              "packid": "102", "params": { "byte": 1, "offset": 3, "len": 1, "tip": "discrete", "description": "Неисправность модуля ММК20 (А1В7) - обобщенная" } },
      { "id": 33554692, "name": "102_SHS51_FaultMMK20_A1B8",              "packid": "102", "params": { "byte": 1, "offset": 4, "len": 1, "tip": "discrete", "description": "Неисправность модуля ММК20 (А1В8) - обобщённая" } },
      { "id": 33554693, "name": "102_SHS51_ServiceableMMK165_A1B9",       "packid": "102", "params": { "byte": 1, "offset": 5, "len": 1, "tip": "discrete", "description": "Исправность модуля ММК165 (А1В9)" } },
      { "id": 33554694, "name": "102_SHS51_FaultMMK165_A1B9",             "packid": "102", "params": { "byte": 1, "offset": 6, "len": 1, "tip": "discrete", "description": "Неисправность модуля ММК165 (А1В9) - обобщённая" } },
      { "id": 33554695, "name": "102_SHS51_ServiceableMMK166_A1B10",      "packid": "102", "params": { "byte": 1, "offset": 7, "len": 1, "tip": "discrete", "description": "Исправность модуля ММК166 (А1В10)" } },
      { "id": 33554944, "name": "102_SHS51_FaultMMK166_A1B10",            "packid": "102", "params": { "byte": 2, "offset": 0, "len": 1, "tip": "discrete", "description": "Неисправность модуля ММК166 (А1В10) - обобщённая" } },
      { "id": 33554945, "name": "102_SHS51_ServiceableMMK53_A1B12",       "packid": "102", "params": { "byte": 2, "offset": 1, "len": 1, "tip": "discrete", "description": "Исправность модуля ММК53 (А1В12)" } },
      { "id": 33554946, "name": "102_SHS51_FaultMMK53_A1B12",             "packid": "102", "params": { "byte": 2, "offset": 2, "len": 1, "tip": "discrete", "description": "Неисправность модуля ММК53 (А1В12) - обобщённая" } },
      { "id": 33554947, "name": "102_SHS51_ServiceableMMK165_A1B13",      "packid": "102", "params": { "byte": 2, "offset": 3, "len": 1, "tip": "discrete", "description": "Исправность модуля ММК165 (А1В13)" } },
      { "id": 33554949, "name": "102_SHS51_FaultMMK165_A1B13",            "packid": "102", "params": { "byte": 2, "offset": 5, "len": 1, "tip": "discrete", "description": "Неисправность модуля ММК165 (А1В13) - обобщённая" } },
      { "id": 33554950, "name": "102_SHS51_FaultMMK97_A1B15",             "packid": "102", "params": { "byte": 2, "offset": 6, "len": 1, "tip": "discrete", "description": "Неисправность модуля ММК97 (А1В15) (по Т хол. спая > 100 °С в МО )" } },
      { "id": 33554951, "name": "102_SHS51_ServiceableMMK163_A1B16",      "packid": "102", "params": { "byte": 2, "offset": 7, "len": 1, "tip": "discrete", "description": "Исправность модуля ММК163 (А1В16)" } },
      { "id": 33555201, "name": "102_SHS51_FaultMMK163_A1B16",            "packid": "102", "params": { "byte": 3, "offset": 1, "len": 1, "tip": "discrete", "description": "Неисправность модуля ММК163 (А1В16) - обобщённая" } },
      { "id": 33555202, "name": "102_SHS51_FaultMPV_Other",               "packid": "102", "params": { "byte": 3, "offset": 2, "len": 1, "tip": "discrete", "description": "Неисправность модуля MPV-DC-20C1 (А20) (парного канала)" } },
      { "id": 33555203, "name": "102_SHS51_ServiceableMPV_Other",         "packid": "102", "params": { "byte": 3, "offset": 3, "len": 1, "tip": "discrete", "description": "Исправность модуля MPV-DC-20C1 (А20) (парного канала)" } },
      { "id": 33555204, "name": "102_SHS51_FaultMTKM_A23",                "packid": "102", "params": { "byte": 3, "offset": 4, "len": 1, "tip": "discrete", "description": "Неисправность модуля MТКМ (А23)" } },
      { "id": 33555205, "name": "102_SHS51_FaultMVU12_A28",               "packid": "102", "params": { "byte": 3, "offset": 5, "len": 1, "tip": "discrete", "description": "Неисправность модуля MВУ12 (А28)" } },
      { "id": 33555206, "name": "102_SHS51_FaultMVU11_A30",               "packid": "102", "params": { "byte": 3, "offset": 6, "len": 1, "tip": "discrete", "description": "Неисправность модуля MВУ11 (А30)" } },
      { "id": 33555207, "name": "102_SHS51_FaultMVU11_A31",               "packid": "102", "params": { "byte": 3, "offset": 7, "len": 1, "tip": "discrete", "description": "Неисправность модуля MВУ11 (А31)" } },
      { "id": 33555456, "name": "102_SHS51_FaultMKCHS_A33",               "packid": "102", "params": { "byte": 4, "offset": 0, "len": 1, "tip": "discrete", "description": "Неисправность модуля MКЧС (А33)" } },
      { "id": 33555457, "name": "102_SHS51_FaultSensorFreqKND_A33ch1",    "packid": "102", "params": { "byte": 4, "offset": 1, "len": 1, "tip": "discrete", "description": "Неисправность 1 частотного канала МКЧС (А33)" } },
      { "id": 33555458, "name": "102_SHS51_FaultSensorFreqKVD_A33ch2",    "packid": "102", "params": { "byte": 4, "offset": 2, "len": 1, "tip": "discrete", "description": "Неисправность 2 частотного канала МКЧС (А33)" } },
      { "id": 33555459, "name": "102_SHS51_FaultSensorFreqTV_A33ch3",     "packid": "102", "params": { "byte": 4, "offset": 3, "len": 1, "tip": "discrete", "description": "Неисправность 3 частотного канала МКЧС (А33)" } },
      { "id": 33555460, "name": "102_SHS51_FaultMKI1_A37",                "packid": "102", "params": { "byte": 4, "offset": 4, "len": 1, "tip": "discrete", "description": "Неисправность модуля MКИ1 (А37)" } },
      { "id": 33555461, "name": "102_SHS51_ServiceableMPK12K_A42",        "packid": "102", "params": { "byte": 4, "offset": 5, "len": 1, "tip": "discrete", "description": "Исправность модуля MПК12-К (А42)" } },
      { "id": 33555462, "name": "102_SHS51_FaultMVU16_A45",               "packid": "102", "params": { "byte": 4, "offset": 6, "len": 1, "tip": "discrete", "description": "Неисправность модуля MВУ16-1 (А45)" } },
      { "id": 33555463, "name": "102_SHS51_FaultMVU16_A51",               "packid": "102", "params": { "byte": 4, "offset": 7, "len": 1, "tip": "discrete", "description": "Неисправность модуля MВУ16-1 (А51)" } },
      { "id": 33555712, "name": "102_SHS51_FaultMVU16_A57",               "packid": "102", "params": { "byte": 5, "offset": 0, "len": 1, "tip": "discrete", "description": "Неисправность модуля MВУ16-1 (А57)" } },
      { "id": 33555713, "name": "102_SHS51_FaultMVU16_A63",               "packid": "102", "params": { "byte": 5, "offset": 1, "len": 1, "tip": "discrete", "description": "Неисправность модуля MВУ16-1 (А63)" } },
      { "id": 33555714, "name": "102_SHS51_MainPowerOff",                 "packid": "102", "params": { "byte": 5, "offset": 2, "len": 1, "tip": "discrete", "description": "Отсутствие питания осн. сети ШС5-1-1" } },
      { "id": 33555715, "name": "102_SHS51_Complete",                     "packid": "102", "params": { "byte": 5, "offset": 3, "len": 1, "tip": "discrete", "description": "Комплектность своего прибора ШС5" } },
      { "id": 33555716, "name": "102_SHS51_Fault",                        "packid": "102", "params": { "byte": 5, "offset": 4, "len": 1, "tip": "discrete", "description": "Неисправность своего прибора ШС5" } },
      { "id": 33555717, "name": "102_SHS51_Diagn",                        "packid": "102", "params": { "byte": 5, "offset": 5, "len": 1, "tip": "discrete", "description": "Исправность своего прибора ШС5" } },
      { "id": 33555718, "name": "102_SHS51_ReservePowerOff",              "packid": "102", "params": { "byte": 5, "offset": 6, "len": 1, "tip": "discrete", "description": "Отсутствие питания рез. сети  ШС5-1-1" } }
    ]},

    { "group": "Некомплектность модулей прибора ШС5-1-1 - Входы (Уникальные)", "signals": [
      { "id": 33555968, "name": "102_SHS51_CompleteMVA32_A1B5",           "packid": "102", "params": { "byte": 6, "offset": 0, "len": 1, "tip": "discrete", "description": "Комплектность модуля МВА32-1(А1В5)" } },
      { "id": 33555969, "name": "102_SHS51_CompleteMMK20_A1B6",           "packid": "102", "params": { "byte": 6, "offset": 1, "len": 1, "tip": "discrete", "description": "Комплектность модуля ММК20 (А1В6)" } },
      { "id": 33555970, "name": "102_SHS51_CompleteMMK20_A1B7",           "packid": "102", "params": { "byte": 6, "offset": 2, "len": 1, "tip": "discrete", "description": "Комплектность модуля ММК20 (А1В7)" } },
      { "id": 33555971, "name": "102_SHS51_CompleteMMK20_A1B8",           "packid": "102", "params": { "byte": 6, "offset": 3, "len": 1, "tip": "discrete", "description": "Комплектность модуля ММК20 (А1В8)" } },
      { "id": 33555972, "name": "102_SHS51_CompleteMMK165_A1B9",          "packid": "102", "params": { "byte": 6, "offset": 4, "len": 1, "tip": "discrete", "description": "Комплектность модуля ММК165 (А1В9)" } },
      { "id": 33555973, "name": "102_SHS51_CompleteMMK166_A1B10",         "packid": "102", "params": { "byte": 6, "offset": 5, "len": 1, "tip": "discrete", "description": "Комплектность модуля ММК166 (А1В10)" } },
      { "id": 33555974, "name": "102_SHS51_CompleteMMK53_A1B12",          "packid": "102", "params": { "byte": 6, "offset": 6, "len": 1, "tip": "discrete", "description": "Комплектность модуля ММК53 (А1В12)" } },
      { "id": 33555975, "name": "102_SHS51_CompleteMMK165_A1B13",         "packid": "102", "params": { "byte": 6, "offset": 7, "len": 1, "tip": "discrete", "description": "Комплектность модуля ММК165 (А1В13)" } },
      { "id": 33556224, "name": "102_SHS51_CompleteMMK97_A1B15",          "packid": "102", "params": { "byte": 7, "offset": 0, "len": 1, "tip": "discrete", "description": "Комплектность модуля ММК97 (А1В15)" } },
      { "id": 33556225, "name": "102_SHS51_CompleteMMK163_A1B16",         "packid": "102", "params": { "byte": 7, "offset": 1, "len": 1, "tip": "discrete", "description": "Комплектность модуля ММК163 (А1В16)" } },
      { "id": 33556226, "name": "102_SHS51_CompleteMPV_Other",            "packid": "102", "params": { "byte": 7, "offset": 2, "len": 1, "tip": "discrete", "description": "Комплектность модуля MPV-DC-20C1 (А20) (парного канала)" } },
      { "id": 33556227, "name": "102_SHS51_CompleteMTKM_A23",             "packid": "102", "params": { "byte": 7, "offset": 3, "len": 1, "tip": "discrete", "description": "Комплектность модуля MТКМ (А23)" } },
      { "id": 33556228, "name": "102_SHS51_CompleteMVU12_A28",            "packid": "102", "params": { "byte": 7, "offset": 4, "len": 1, "tip": "discrete", "description": "Комплектность модуля MВУ12 (А28)" } },
      { "id": 33556229, "name": "102_SHS51_CompleteMVU11_A30",            "packid": "102", "params": { "byte": 7, "offset": 5, "len": 1, "tip": "discrete", "description": "Комплектность модуля MВУ11 (А30)" } },
      { "id": 33556230, "name": "102_SHS51_CompleteMVU11_A31",            "packid": "102", "params": { "byte": 7, "offset": 6, "len": 1, "tip": "discrete", "description": "Комплектность модуля MВУ11 (А31)" } },
      { "id": 33556231, "name": "102_SHS51_CompleteMKCHS_A33",            "packid": "102", "params": { "byte": 7, "offset": 7, "len": 1, "tip": "discrete", "description": "Комплектность модуля MКЧС (А33)" } },
      { "id": 33556480, "name": "102_SHS51_CompleteMVR6_A35",             "packid": "102", "params": { "byte": 8, "offset": 0, "len": 1, "tip": "discrete", "description": "Комплектность модуля MВР6 (А35)" } },
      { "id": 33556481, "name": "102_SHS51_CompleteMKI1_A37",             "packid": "102", "params": { "byte": 8, "offset": 1, "len": 1, "tip": "discrete", "description": "Комплектность модуля MКИ1 (А37)" } },
      { "id": 33556482, "name": "102_SHS51_CompleteMRB_A38",              "packid": "102", "params": { "byte": 8, "offset": 2, "len": 1, "tip": "discrete", "description": "Комплектность модуля MР-Б (А38)" } },
      { "id": 33556483, "name": "102_SHS51_CompleteMPK12K_A42",           "packid": "102", "params": { "byte": 8, "offset": 3, "len": 1, "tip": "discrete", "description": "Комплектность модуля MПК12-К (А42)" } },
      { "id": 33556484, "name": "102_SHS51_CompleteMVU16_A45",            "packid": "102", "params": { "byte": 8, "offset": 4, "len": 1, "tip": "discrete", "description": "Комплектность модуля MВУ16-1 (А45)" } },
      { "id": 33556485, "name": "102_SHS51_CompleteMVU16_A51",            "packid": "102", "params": { "byte": 8, "offset": 5, "len": 1, "tip": "discrete", "description": "Комплектность модуля MВУ16-1 (А51)" } },
      { "id": 33556486, "name": "102_SHS51_CompleteMVU16_A57",            "packid": "102", "params": { "byte": 8, "offset": 6, "len": 1, "tip": "discrete", "description": "Комплектность модуля MВУ16-1 (А57)" } },
      { "id": 33556487, "name": "102_SHS51_CompleteMVU16_A63",            "packid": "102", "params": { "byte": 8, "offset": 7, "len": 1, "tip": "discrete", "description": "Комплектность модуля MВУ16-1 (А63)" } }
    ]},

    { "group": "Неисправность и некомплектность приборов 2ШС5-1 и ШС5-6.1 1-го канала - Входы (Уникальные)", "signals": [
      { "id": 33556992, "name": "102_SHS51_2SHS51_CompleteDrive",         "packid": "102", "params": { "byte": 10, "offset": 0, "len": 1, "tip": "discrete", "description": "Комплектность 1 канала привода (прибор 2ШС5-1)" } },
      { "id": 33556994, "name": "102_SHS51_SHS56_ServiceableMSUB",        "packid": "102", "params": { "byte": 10, "offset": 2, "len": 1, "tip": "discrete", "description": "Исправность МСУБ 1 канала управления (ШС5-6.1)" } },
      { "id": 33556995, "name": "102_SHS51_SHS56_FaultMSUB",              "packid": "102", "params": { "byte": 10, "offset": 3, "len": 1, "tip": "discrete", "description": "Неисправность МСУБ 1 канала управления (ШС5-6.1)" } },
      { "id": 33556996, "name": "102_SHS51_SHS56_CompleteMSUB",           "packid": "102", "params": { "byte": 10, "offset": 4, "len": 1, "tip": "discrete", "description": "Комплектность МСУБ 1 канала управления (ШС5-6.1)" } },
      { "id": 33556997, "name": "102_SHS51_SHS56_ServiceableMVT3",        "packid": "102", "params": { "byte": 10, "offset": 5, "len": 1, "tip": "discrete", "description": "Исправность МВТ3 1 канала управления (ШС5-6.1)" } },
      { "id": 33556998, "name": "102_SHS51_SHS56_FaultMVT3",              "packid": "102", "params": { "byte": 10, "offset": 6, "len": 1, "tip": "discrete", "description": "Неисправность МВТ3 1 канала управления (ШС5-6.1)" } }
    ]},

    { "group": "Сигнализация модулей прибора ШС4.1 1 канала - Входы (Уникальные)", "signals": [
      { "id": 33557504, "name": "102_SHS51_SHS4_MainPowerOn",             "packid": "102", "params": { "byte": 12, "offset": 0, "len": 1, "tip": "discrete", "description": "Наличие основной сети" } },
      { "id": 33557505, "name": "102_SHS51_SHS4_ReservePowerOn",          "packid": "102", "params": { "byte": 12, "offset": 1, "len": 1, "tip": "discrete", "description": "Наличие Резервной сети" } },
      { "id": 33557506, "name": "102_SHS51_SHS4_Fault1MP350",             "packid": "102", "params": { "byte": 12, "offset": 2, "len": 1, "tip": "discrete", "description": "Неисправность МП350 (1)" } },
      { "id": 33557507, "name": "102_SHS51_SHS4_Fault2MP350",             "packid": "102", "params": { "byte": 12, "offset": 3, "len": 1, "tip": "discrete", "description": "Неисправность МП350 (2)" } },
      { "id": 33557508, "name": "102_SHS51_SHS4_Fault3MP350",             "packid": "102", "params": { "byte": 12, "offset": 4, "len": 1, "tip": "discrete", "description": "Неисправность МП350 (3)" } },
      { "id": 33557509, "name": "102_SHS51_SHS4_Fault4MP350",             "packid": "102", "params": { "byte": 12, "offset": 5, "len": 1, "tip": "discrete", "description": "Неисправность МП350 (4)" } },
      { "id": 33557510, "name": "102_SHS51_SHS4_Fault1MP500",             "packid": "102", "params": { "byte": 12, "offset": 6, "len": 1, "tip": "discrete", "description": "Неисправность МП500" } },
      { "id": 33557511, "name": "102_SHS51_SHS4_FaultMP150",              "packid": "102", "params": { "byte": 12, "offset": 7, "len": 1, "tip": "discrete", "description": "Неисправность МП150" } },
      { "id": 33557760, "name": "102_SHS51_SHS4_LowRis1MP350",            "packid": "102", "params": { "byte": 13, "offset": 0, "len": 1, "tip": "discrete", "description": "Пониженное сопротивление изоляции МП350 (1)" } },
      { "id": 33557761, "name": "102_SHS51_SHS4_LowRis2MP350",            "packid": "102", "params": { "byte": 13, "offset": 1, "len": 1, "tip": "discrete", "description": "Пониженное сопротивление изоляции МП350 (2)" } },
      { "id": 33557762, "name": "102_SHS51_SHS4_LowRis3MP350",            "packid": "102", "params": { "byte": 13, "offset": 2, "len": 1, "tip": "discrete", "description": "Пониженное сопротивление изоляции МП350 (3)" } },
      { "id": 33557763, "name": "102_SHS51_SHS4_LowRis4MP350",            "packid": "102", "params": { "byte": 13, "offset": 3, "len": 1, "tip": "discrete", "description": "Пониженное сопротивление изоляции МП350 (4)" } },
      { "id": 33557764, "name": "102_SHS51_SHS4_LowRis1MP500",            "packid": "102", "params": { "byte": 13, "offset": 4, "len": 1, "tip": "discrete", "description": "Пониженное сопротивление изоляции МП500 (1)" } },
      { "id": 33557765, "name": "102_SHS51_SHS4_LowRisMP150",             "packid": "102", "params": { "byte": 13, "offset": 5, "len": 1, "tip": "discrete", "description": "Пониженное сопротивление изоляции МП150" } },
      { "id": 33557766, "name": "102_SHS51_SHS4_WorkFromAB",              "packid": "102", "params": { "byte": 13, "offset": 6, "len": 1, "tip": "discrete", "description": "Работа от АБ" } },
      { "id": 33557767, "name": "102_SHS51_SHS4_ABEmergDischarged",       "packid": "102", "params": { "byte": 13, "offset": 7, "len": 1, "tip": "discrete", "description": "Аварийный разряд АБ" } },
      { "id": 33558016, "name": "102_SHS51_SHS4_ABDischarged",            "packid": "102", "params": { "byte": 14, "offset": 0, "len": 1, "tip": "discrete", "description": "АБ разряжена" } },
      { "id": 33558017, "name": "102_SHS51_SHS4_ABCharged",               "packid": "102", "params": { "byte": 14, "offset": 1, "len": 1, "tip": "discrete", "description": "АБ заряжена" } },
      { "id": 33558018, "name": "102_SHS51_SHS4_ChargingAB",              "packid": "102", "params": { "byte": 14, "offset": 2, "len": 1, "tip": "discrete", "description": "Заряд АБ" } },
      { "id": 33558019, "name": "102_SHS51_SHS4_Fault1MKZB",              "packid": "102", "params": { "byte": 14, "offset": 3, "len": 1, "tip": "discrete", "description": "Неисправность МКЗБ" } },
      { "id": 33558020, "name": "102_SHS51_SHS4_Fault_Common",            "packid": "102", "params": { "byte": 14, "offset": 4, "len": 1, "tip": "discrete", "description": "Обобщенная неисправность своего прибора ШС4" } },
      { "id": 33558021, "name": "102_SHS51_SHS4_Complete_Common",         "packid": "102", "params": { "byte": 14, "offset": 5, "len": 1, "tip": "discrete", "description": "Обобщенная комплектность своего прибора ШС4" } }
    ]},

    { "group": "Контроль целостности ПО прибора ШС5-1-1", "signals": [
      { "id": 33558784, "name": "102_sgn_SoFtWaReTeSt_ShS5_1",            "packid": "102", "params": { "byte": 17, "offset": 0, "len": 1, "tip": "discrete", "description": "Идет проверка ПО ШС5-1-1" } },
      { "id": 33558785, "name": "102_sgn_SoFtWaRe_Test_ShS5_1_Not_Maked", "packid": "102", "params": { "byte": 17, "offset": 1, "len": 1, "tip": "discrete", "description": "Тест ПО ШС5-1-1 не проводился" } },
      { "id": 33558786, "name": "102_sgn_SoFtWaRe_State_ShS5_1",          "packid": "102", "params": { "byte": 17, "offset": 2, "len": 1, "tip": "discrete", "description": "Состояние ПО ШС5-1-1 (1 == не изменено)" } },
      { "id": 33558787, "name": "102_sgn_SoFtWaRe_MeTrOl_State_ShS5_1",   "packid": "102", "params": { "byte": 17, "offset": 3, "len": 1, "tip": "discrete", "description": "Состояние МЗЧ ПО ШС5-1-1 (1 == не изменено)" } },
      { "id": 33559040, "name": "102_SHS51_CRC_Etalon",                   "packid": "102", "params": { "byte": 18, "offset": 0, "len": 32, "tip": "word", "description": "Эталонная контрольная сумма ПО ШС5-1-1" } },
      { "id": 33560064, "name": "102_SHS51_CRC_Current",                  "packid": "102", "params": { "byte": 22, "offset": 0, "len": 32, "tip": "word", "description": "Текущая контрольная сумма ПО ШС5-1-1" } },
      { "id": 33561088, "name": "102_SHS51_CRC_Metrology_Etalon",         "packid": "102", "params": { "byte": 26, "offset": 0, "len": 32, "tip": "word", "description": "Эталонная контрольная сумма метрологически значимой части ПО ШС5-1-1" } },
      { "id": 33562112, "name": "102_SHS51_CRC_Metrology_Current",        "packid": "102", "params": { "byte": 30, "offset": 0, "len": 32, "tip": "word", "description": "Текущая контрольная сумма метрологически значимой части ПО ШС5-1-1" } },
      { "id": 33563136, "name": "102_IHD_ChkSum51",                       "packid": "102", "params": { "byte": 34, "offset": 0, "len": 32, "tip": "word", "description": "Контрольная сумма файла ИХД прибора ШС5-1-1" } },
      { "id": 33564160, "name": "102_NHD_ChkSum51",                       "packid": "102", "params": { "byte": 38, "offset": 0, "len": 32, "tip": "word", "description": "Контрольная сумма файла НХД прибора ШС5-1-1" } }
    ]},

    { "group": "Диагностические данные прибора ШС5-1-1", "signals": [
      { "id": 33565184, "name": "102_PRCSS_BRKN_51",                      "packid": "102", "params": { "byte": 42, "offset": 0, "len": 1, "tip": "discrete", "description": "Признак падения процессов на приборе ШС5-1-1" } },
      { "id": 33565185, "name": "102_sgn_MTK_State_ShS5_1",               "packid": "102", "params": { "byte": 42, "offset": 1, "len": 1, "tip": "discrete", "description": "Состояние ТС (МТК) (1 == в порядке)" } },
      { "id": 33565186, "name": "102_sgn_MKI_State_ShS5_1",               "packid": "102", "params": { "byte": 42, "offset": 2, "len": 1, "tip": "discrete", "description": "Состояние ТС (МКИ) (1 == в порядке)" } },
      { "id": 33565188, "name": "102_SHS51_APS_i052",                     "packid": "102", "params": { "byte": 42, "offset": 4, "len": 1, "tip": "discrete", "description": "ШС5-1-1: Восстановлены данные НХД по принципу 2/3" } },
      { "id": 33565189, "name": "102_SHS51_APS_i053",                     "packid": "102", "params": { "byte": 42, "offset": 5, "len": 1, "tip": "discrete", "description": "ШС5-1-1: Изменены данные НХД по команде ПРП" } },
      { "id": 33565190, "name": "102_SHS51_APS_e158",                     "packid": "102", "params": { "byte": 42, "offset": 6, "len": 1, "tip": "discrete", "description": "ШС5-1-1: Рассогласование НХД в приборе" } },
      { "id": 33565191, "name": "102_SHS51_APS_i055",                     "packid": "102", "params": { "byte": 42, "offset": 7, "len": 1, "tip": "discrete", "description": "ШС5-1-1: Восстановлены данные ИХД по принципу 2/3" } },
      { "id": 33565440, "name": "102_SHS51_APS_i056",                     "packid": "102", "params": { "byte": 43, "offset": 0, "len": 1, "tip": "discrete", "description": "ШС5-1-1: Изменены данные ИХД по команде ПРП" } },
      { "id": 33565441, "name": "102_SHS51_APS_w158",                     "packid": "102", "params": { "byte": 43, "offset": 1, "len": 1, "tip": "discrete", "description": "ШС5-1-1: Рассогласование ИХД в приборе" } },
      { "id": 33565442, "name": "102_sgn_EmergStopGTD51",                 "packid": "102", "params": { "byte": 43, "offset": 2, "len": 1, "tip": "discrete", "description": "Аварийная остановка сформированная ШС5-1-1" } },
      { "id": 33566208, "name": "102_Alive51",                            "packid": "102", "params": { "byte": 46, "offset": 0, "len": 32, "tip": "word", "description": "Признак наличия связи с прибором ШС5-1-1" } },
      { "id": 33567232, "name": "102_SHS51_Active",                       "packid": "102", "params": { "byte": 50, "offset": 0, "len": 32, "tip": "word", "description": "Признак активности ШС5-1-1" } }
    ]},

    { "group": "Данные синхронизируемые м/у приборами", "signals": [
      { "id": 33572352, "name": "102_SHS51_NumbStartSaved",               "packid": "102", "params": { "byte": 70, "offset": 0, "len": 32, "tip": "word", "description": "Порядковый номер пуска, записываемый в файл" } },
      { "id": 33573376, "name": "102_SHS51_OperatTimeSaved",              "packid": "102", "params": { "byte": 74, "offset": 0, "len": 32, "tip": "word", "description": "Текущее значение общей наработки ГТД, записываемое в файл" } },
      { "id": 33574400, "name": "102_SHS51_OperDataFlag",                 "packid": "102", "params": { "byte": 78, "offset": 0, "len": 1, "tip": "discrete", "description": "Признак записи в файл порядкового номера пуска и текущего значения общей наработки ГТД для пассивного канала" } }
    ]}
  ]
}