{
  "signals":
  [
    {"name": "VDR057", "id": 57, "device": 1, "storages": [1], "type": "XDR" , "timeout": 3000, "timeout_value": -1, "timeout_signal_id": -1, "params": {"group":1, "word": 0,  "tag": "400_1_ST_096"},     "description": "Силовая установка, ГЭД фактическая скорость"},
    {"name": "VDR058", "id": 58, "device": 1, "storages": [1], "type": "XDR" , "timeout": 3000, "timeout_value": -1, "timeout_signal_id": -1, "params": {"group":1, "word": 4,  "tag": "400_1_UT_098"},     "description": "Силовая установка,  ГЭД фактический крутящий момент"},
    {"name": "VDR059", "id": 59, "device": 1, "storages": [1], "type": "XDR" , "timeout": 3000, "timeout_value": -1, "timeout_signal_id": -1, "params": {"group":1, "word": 8,  "tag": "400_1_JT_097"},     "description": "Силовая установка, ГЭД фактическая мощность"},
    {"name": "VDR060", "id": 60, "device": 1, "storages": [1], "type": "XDR" , "timeout": 3000, "timeout_value": -1, "timeout_signal_id": -1, "params": {"group":1, "word": 12,  "tag": "400_1_XY_327"},     "description": "POD1 фактический угол поворота"},
    {"name": "VDR061", "id": 61, "device": 1, "storages": [1], "type": "XDR" , "timeout": 3000, "timeout_value": -1, "timeout_signal_id": -1, "params": {"group":2, "word": 0,  "tag": "404_1_ST_100"},     "description": "ПУ1 фактический шаг"},
    {"name": "VDR062", "id": 62, "device": 1, "storages": [1], "type": "XDR" , "timeout": 3000, "timeout_value": -1, "timeout_signal_id": -1, "params": {"group":2, "word": 4,  "tag": "404_2_ST_100"},     "description": "ПУ2 фактический шаг"},
    {"name": "VDR063", "id": 63, "device": 1, "storages": [1], "type": "XDR" , "timeout": 3000, "timeout_value": -1, "timeout_signal_id": -1, "params": {"group":2, "word": 8,  "tag": "Swbd_DG_No"},       "description": "ДГ онлайн"},
    {"name": "VDR064", "id": 64, "device": 1, "storages": [1], "type": "XDR" , "timeout": 3000, "timeout_value": -1, "timeout_signal_id": -1, "params": {"group":2, "word": 12,  "tag": "Swbd_Pow_Avail"},   "description": "Мощность В Наличии"},
    {"name": "VDR065", "id": 65, "device": 1, "storages": [1], "type": "XDR" , "timeout": 3000, "timeout_value": -1, "timeout_signal_id": -1, "params": {"group":3, "word": 0,  "tag": "400_2_ST_096"},     "description": "Силовая установка,  ГЭД фактическая скорость"},
    {"name": "VDR066", "id": 66, "device": 1, "storages": [1], "type": "XDR" , "timeout": 3000, "timeout_value": -1, "timeout_signal_id": -1, "params": {"group":3, "word": 4,  "tag": "400_2_UT_098"},     "description": "Силовая установка,   ГЭД фактический крутящий момент"},
    {"name": "VDR067", "id": 67, "device": 1, "storages": [1], "type": "XDR" , "timeout": 3000, "timeout_value": -1, "timeout_signal_id": -1, "params": {"group":3, "word": 8,  "tag": "400_2_JT_097"},     "description": "Силовая установка, ГЭД фактическая мощность"},
    {"name": "VDR068", "id": 68, "device": 1, "storages": [1], "type": "XDR" , "timeout": 3000, "timeout_value": -1, "timeout_signal_id": -1, "params": {"group":3, "word": 12,  "tag": "400_2_XY_327"},     "description": "POD2 фактический угол поворота"}
  ]
}